qiskit_alice_bob_provider/__init__.py
qiskit_alice_bob_provider/custom_instructions.py
qiskit_alice_bob_provider/errors.py
qiskit_alice_bob_provider/local/__init__.py
qiskit_alice_bob_provider/local/backend.py
qiskit_alice_bob_provider/local/coupling_maps.py
qiskit_alice_bob_provider/local/instruction_durations.py
qiskit_alice_bob_provider/local/job.py
qiskit_alice_bob_provider/local/proc_to_qiskit.py
qiskit_alice_bob_provider/local/provider.py
qiskit_alice_bob_provider/local/quantum_errors.py
qiskit_alice_bob_provider/local/readout_errors.py
qiskit_alice_bob_provider/local/target.py
qiskit_alice_bob_provider/local/patch/__init__.py
qiskit_alice_bob_provider/local/patch/local_noise_pass.py
qiskit_alice_bob_provider/local/resources/lescanne_2020.json
qiskit_alice_bob_provider/plugins/__init__.py
qiskit_alice_bob_provider/plugins/ab_asap.py
qiskit_alice_bob_provider/plugins/sk_synthesis.py
qiskit_alice_bob_provider/plugins/state_preparation.py
qiskit_alice_bob_provider/processor/__init__.py
qiskit_alice_bob_provider/processor/description.py
qiskit_alice_bob_provider/processor/interpolated_cat.py
qiskit_alice_bob_provider/processor/logical_cat.py
qiskit_alice_bob_provider/processor/physical_cat.py
qiskit_alice_bob_provider/processor/utils.py
qiskit_alice_bob_provider/processor/serialization/__init__.py
qiskit_alice_bob_provider/processor/serialization/interpolate.py
qiskit_alice_bob_provider/processor/serialization/model.py
qiskit_alice_bob_provider/remote/__init__.py
qiskit_alice_bob_provider/remote/backend.py
qiskit_alice_bob_provider/remote/display.py
qiskit_alice_bob_provider/remote/job.py
qiskit_alice_bob_provider/remote/provider.py
qiskit_alice_bob_provider/remote/qir_to_qiskit.py
qiskit_alice_bob_provider/remote/api/__init__.py
qiskit_alice_bob_provider/remote/api/client.py
qiskit_alice_bob_provider/remote/api/jobs.py
qiskit_alice_bob_provider/remote/api/models.py
qiskit_alice_bob_provider/remote/api/targets.py
qiskit_alice_bob_provider/remote/api/version.py
qiskit_alice_bob_provider-1.2.0.dist-info/licenses/LICENSE
qiskit_alice_bob_provider-1.2.0.dist-info/METADATA
qiskit_alice_bob_provider-1.2.0.dist-info/WHEEL
qiskit_alice_bob_provider-1.2.0.dist-info/entry_points.txt
qiskit_alice_bob_provider-1.2.0.dist-info/top_level.txt
qiskit_alice_bob_provider-1.2.0.dist-info/RECORD
