Metadata-Version: 2.4
Name: qiskit_alice_bob_provider
Version: 1.2.0
Summary: Provider for running Qiskit circuits on Alice & Bob QPUs and simulators
Author: Alice & Bob Software Team
License: Apache 2.0
Project-URL: Homepage, https://github.com/Alice-Bob-SW/qiskit-alice-bob-provider
Project-URL: Alice & Bob, https://alice-bob.com/
Keywords: Qiskit,Alice & Bob,Quantum,SDK
Classifier: Environment :: Console
Classifier: License :: OSI Approved :: Apache Software License
Classifier: Intended Audience :: Developers
Classifier: Intended Audience :: Science/Research
Classifier: Operating System :: Microsoft :: Windows
Classifier: Operating System :: MacOS
Classifier: Operating System :: POSIX :: Linux
Classifier: Programming Language :: Python :: 3 :: Only
Classifier: Programming Language :: Python :: 3.9
Classifier: Programming Language :: Python :: 3.10
Classifier: Programming Language :: Python :: 3.11
Classifier: Programming Language :: Python :: 3.12
Classifier: Programming Language :: Python :: 3.13
Classifier: Topic :: Scientific/Engineering :: Physics
Requires-Python: <3.14,>=3.9
License-File: LICENSE
Requires-Dist: ipython
Requires-Dist: ipywidgets
Requires-Dist: pydantic>=2.0
Requires-Dist: requests>=1.26
Requires-Dist: qiskit<2.0,>=1.3.1
Requires-Dist: qiskit-aer<0.18.0,>=0.16.1
Requires-Dist: qiskit-qir-alice-bob-fork==0.5.0
Requires-Dist: tenacity
Provides-Extra: dev
Requires-Dist: black==23.1.0; extra == "dev"
Requires-Dist: build==0.10.0; extra == "dev"
Requires-Dist: codespell==2.2.2; extra == "dev"
Requires-Dist: coverage==7.2.2; extra == "dev"
Requires-Dist: flake8>=5.0.4; extra == "dev"
Requires-Dist: flake8-quotes==3.4.0; extra == "dev"
Requires-Dist: isort>=5.11.5; extra == "dev"
Requires-Dist: mock==5.1.0; extra == "dev"
Requires-Dist: mypy==1.0.0; extra == "dev"
Requires-Dist: mypy-extensions==1.0.0; extra == "dev"
Requires-Dist: pre-commit>=2.21.0; extra == "dev"
Requires-Dist: pylint==3.2.7; extra == "dev"
Requires-Dist: pytest==7.2.1; extra == "dev"
Requires-Dist: python-semantic-release==9.18.1; extra == "dev"
Requires-Dist: requests==2.32.3; extra == "dev"
Requires-Dist: requests-mock==1.10.0; extra == "dev"
Requires-Dist: traitlets==5.14.3; extra == "dev"
Requires-Dist: twine==5.1.1; extra == "dev"
Requires-Dist: types-mock==5.1.0; extra == "dev"
Requires-Dist: types-setuptools==70.0.0.20240524; extra == "dev"
Requires-Dist: types-requests==2.30.0.0; extra == "dev"
Dynamic: license-file
